MANIFEST.in
README.rst
setup.py
docs/HISTORY.txt
docs/INSTALL.txt
docs/LICENSE.GPL
docs/LICENSE.txt
docs/TODO.txt
unice/.DS_Store
unice/__init__.py
unice.portlet.boutique.egg-info/PKG-INFO
unice.portlet.boutique.egg-info/SOURCES.txt
unice.portlet.boutique.egg-info/dependency_links.txt
unice.portlet.boutique.egg-info/entry_points.txt
unice.portlet.boutique.egg-info/namespace_packages.txt
unice.portlet.boutique.egg-info/not-zip-safe
unice.portlet.boutique.egg-info/requires.txt
unice.portlet.boutique.egg-info/top_level.txt
unice/portlet/.DS_Store
unice/portlet/__init__.py
unice/portlet/boutique/.DS_Store
unice/portlet/boutique/__init__.py
unice/portlet/boutique/boutiqueportlet.pt
unice/portlet/boutique/boutiqueportlet.py
unice/portlet/boutique/configure.zcml
unice/portlet/boutique/prestashop.py
unice/portlet/boutique/vocabularies.py
unice/portlet/boutique/browser/.DS_Store
unice/portlet/boutique/browser/__init__.py
unice/portlet/boutique/browser/configure.zcml
unice/portlet/boutique/browser/stylesheets/styles.css
unice/portlet/boutique/profiles/.DS_Store
unice/portlet/boutique/profiles/default/cssregistry.xml
unice/portlet/boutique/profiles/default/metadata.xml
unice/portlet/boutique/profiles/default/portlets.xml
unice/portlet/boutique/tests/__init__.py
unice/portlet/boutique/tests/base.py
unice/portlet/boutique/tests/test_portlet.py